utils/check_latest_version.py
utils/download_binaries.py
utils/update_version.py
vespacli/__init__.py
vespacli/__main__.py
vespacli/_version_generated.py
vespacli/go-binaries/vespa-cli_8.631.39_sha256sums.txt
vespacli/go-binaries/vespa-cli_8.631.39_darwin_amd64/LICENSE
vespacli/go-binaries/vespa-cli_8.631.39_darwin_amd64/bin/vespa
vespacli/go-binaries/vespa-cli_8.631.39_darwin_amd64/share/man/man1/vespa-activate.1
vespacli/go-binaries/vespa-cli_8.631.39_darwin_amd64/share/man/man1/vespa-auth-api-key.1
vespacli/go-binaries/vespa-cli_8.631.39_darwin_amd64/share/man/man1/vespa-auth-cert-add.1
vespacli/go-binaries/vespa-cli_8.631.39_darwin_amd64/share/man/man1/vespa-auth-cert.1
vespacli/go-binaries/vespa-cli_8.631.39_darwin_amd64/share/man/man1/vespa-auth-login.1
vespacli/go-binaries/vespa-cli_8.631.39_darwin_amd64/share/man/man1/vespa-auth-logout.1
vespacli/go-binaries/vespa-cli_8.631.39_darwin_amd64/share/man/man1/vespa-auth-show.1
vespacli/go-binaries/vespa-cli_8.631.39_darwin_amd64/share/man/man1/vespa-auth.1
vespacli/go-binaries/vespa-cli_8.631.39_darwin_amd64/share/man/man1/vespa-clone.1
vespacli/go-binaries/vespa-cli_8.631.39_darwin_amd64/share/man/man1/vespa-config-get.1
vespacli/go-binaries/vespa-cli_8.631.39_darwin_amd64/share/man/man1/vespa-config-set.1
vespacli/go-binaries/vespa-cli_8.631.39_darwin_amd64/share/man/man1/vespa-config-unset.1
vespacli/go-binaries/vespa-cli_8.631.39_darwin_amd64/share/man/man1/vespa-config.1
vespacli/go-binaries/vespa-cli_8.631.39_darwin_amd64/share/man/man1/vespa-curl.1
vespacli/go-binaries/vespa-cli_8.631.39_darwin_amd64/share/man/man1/vespa-deploy.1
vespacli/go-binaries/vespa-cli_8.631.39_darwin_amd64/share/man/man1/vespa-destroy.1
vespacli/go-binaries/vespa-cli_8.631.39_darwin_amd64/share/man/man1/vespa-document-get.1
vespacli/go-binaries/vespa-cli_8.631.39_darwin_amd64/share/man/man1/vespa-document-put.1
vespacli/go-binaries/vespa-cli_8.631.39_darwin_amd64/share/man/man1/vespa-document-remove.1
vespacli-8.631.39.dist-info/licenses/LICENSE
vespacli-8.631.39.dist-info/METADATA
vespacli-8.631.39.dist-info/WHEEL
vespacli-8.631.39.dist-info/entry_points.txt
vespacli-8.631.39.dist-info/top_level.txt
vespacli-8.631.39.dist-info/RECORD
