Metadata-Version: 2.4
Name: vespacli
Version: 8.631.39
Summary: A Python wrapper for Vespa CLI tools, supporting multiple platforms.
Author-email: Thomas Thoresen <thomas@vespa.ai>
License:                                  Apache License
Project-URL: documentation, https://docs.vespa.ai/en/vespa-cli.html
Project-URL: homepage, https://pypi.org/project/vespacli/
Project-URL: repository, https://github.com/pyvespa/vespacli
Keywords: vespa,cli,wrapper
Classifier: Programming Language :: Python :: 3
Classifier: License :: OSI Approved :: Apache Software License
Classifier: Operating System :: OS Independent
License-File: LICENSE
Provides-Extra: build
Requires-Dist: setuptools==78.1.1; extra == "build"
Requires-Dist: build==1.0.3; extra == "build"
Requires-Dist: twine==5.1.1; extra == "build"
Requires-Dist: toml==0.10.2; extra == "build"
Requires-Dist: requests>=2.32.3; extra == "build"
Dynamic: license-file
